duplicate_detector/__init__.py
duplicate_detector/__main__.py
duplicate_detector/duplicateDetector.py
duplicate_detector/explorer.py
duplicate_detector/photoSorter.py
duplicate_detector/photofile.py
duplicate_detector-0.0.7.data/scripts/duplicate_detector
duplicate_detector-0.0.7.dist-info/LICENSE
duplicate_detector-0.0.7.dist-info/METADATA
duplicate_detector-0.0.7.dist-info/WHEEL
duplicate_detector-0.0.7.dist-info/top_level.txt
duplicate_detector-0.0.7.dist-info/RECORD
