Metadata-Version: 2.1
Name: duplicate-detector
Version: 0.0.7
Summary: A small duplicate handler CLI tool.
Home-page: https://github.com/Nathanmalnoury/duplicate-detector
Author: Nathan Malnoury
Author-email: n.malnoury@gmail.com
License: UNKNOWN
Platform: UNKNOWN
Classifier: Programming Language :: Python :: 3.8
Classifier: License :: OSI Approved :: MIT License
Classifier: Development Status :: 4 - Beta
Classifier: Environment :: Console
Requires-Python: >=3.8
Requires-Dist: Pillow
Requires-Dist: click
Requires-Dist: tqdm (==4.46)
